rkvst_receipt_scitt/__init__.py
rkvst_receipt_scitt/attribute_decoder.py
rkvst_receipt_scitt/elementmetadata.py
rkvst_receipt_scitt/ethproofs.py
rkvst_receipt_scitt/exceptions.py
rkvst_receipt_scitt/khipureceipt.py
rkvst_receipt_scitt/namedproofs.py
rkvst_receipt_scitt/receipt.py
rkvst_receipt_scitt/receiptdecoder.py
rkvst_receipt_scitt/simplehashreceipt.py
rkvst_receipt_scitt/trie_alg.py
rkvst_receipt_scitt/v1.py
rkvst_receipt_scitt-0.3.0a0.dist-info/LICENSE
rkvst_receipt_scitt-0.3.0a0.dist-info/METADATA
rkvst_receipt_scitt-0.3.0a0.dist-info/WHEEL
rkvst_receipt_scitt-0.3.0a0.dist-info/entry_points.txt
rkvst_receipt_scitt-0.3.0a0.dist-info/top_level.txt
rkvst_receipt_scitt-0.3.0a0.dist-info/RECORD
