Metadata-Version: 2.1
Name: rkvst-receipt-scitt
Version: 0.3.0a0
Summary: RKVST Scitt Receipt Verification in python
Home-page: https://github.com/rkvst/rkvst-receipt-scitt
Author: RKVST Inc.
Author-email: support@rkvst.com
License: MIT
Project-URL: Source, https://github.com/rkvst/rkvst-receipt-scitt
Project-URL: Tracker, https://github.com/rkvst/rkvst-receipt-scitt/issues
Classifier: Development Status :: 4 - Beta
Classifier: Environment :: Console
Classifier: Intended Audience :: Developers
Classifier: License :: OSI Approved :: MIT License
Classifier: Operating System :: POSIX :: Linux
Classifier: Programming Language :: Python :: 3.7
Classifier: Topic :: Utilities
Requires-Python: >=3.7
License-File: LICENSE
Requires-Dist: trie ~=2.1.0
Requires-Dist: pycose ~=1.0.1
Requires-Dist: cbor2 ~=5.4.6
Requires-Dist: rfc3339 ~=6.2
Requires-Dist: eth-hash[pycryptodome] ~=0.5.1
